canswim/__init__.py
canswim/__main__.py
canswim/constants.py
canswim/covariates.py
canswim/forecast.py
canswim/gather_data.py
canswim/hfhub.py
canswim/model.py
canswim/model_search.py
canswim/targets.py
canswim/train.py
canswim/dashboard/__init__.py
canswim/dashboard/advanced.py
canswim/dashboard/charts.py
canswim/dashboard/scans.py
canswim-0.0.20250107.dist-info/LICENSE
canswim-0.0.20250107.dist-info/METADATA
canswim-0.0.20250107.dist-info/WHEEL
canswim-0.0.20250107.dist-info/top_level.txt
canswim-0.0.20250107.dist-info/RECORD
