Metadata-Version: 2.1
Name: canswim
Version: 0.0.20250107
Summary: "Developer toolkit for CANSLIM investment style practitioners"
Author: Ivelin Ivanov
Author-email: ivelin117@gmail.com
License: Apache-2.0
Keywords: stock market,analytics
Classifier: Programming Language :: Python :: 3
Requires-Python: >=3.10
License-File: LICENSE
Requires-Dist: u8darts[torch]==0.27.2
Requires-Dist: numpy<2
Requires-Dist: yfinance[nospam]
Requires-Dist: pandas_market_calendars
Requires-Dist: fmpsdk
Requires-Dist: optuna==3.4.0
Requires-Dist: huggingface_hub
Requires-Dist: gradio
Requires-Dist: loguru
Requires-Dist: duckdb
Requires-Dist: pytest
Requires-Dist: pytest-cov
